{
  "heros": [
    {
      "id": 1,
      "name": "李白",
      "avatar": "http://127.0.0.1:5000/uploads/196.jpg"
    },
    {
      "id": 2,
      "name": "刘备",
      "avatar": "http://127.0.0.1:5000/uploads/196.jpg"
    },
    {
      "id": 3,
      "name": "李白",
      "avatar": "http://127.0.0.1:5000/uploads/196.jpg"
    },
    {
      "name": "张飞",
      "avatar": "http://127.0.0.1:5000/uploads/196.jpg",
      "id": 4
    },
    {
      "name": "哈哈",
      "avatar": "http://127.0.0.1:5000/uploads/196.jpg",
      "id": 5
    },
    {
      "name": "dsada",
      "avatar": "dsadsa",
      "id": 6
    },
    {
      "name": "李白白",
      "avatar": "http://127.0.0.1:5000/uploads/196.jpg",
      "id": 7
    },
    {
      "name": "",
      "avatar": "",
      "id": 8
    }
  ]
}